mongospecs/__init__.py
mongospecs/attrs.py
mongospecs/base.py
mongospecs/helpers/__init__.py
mongospecs/helpers/bson.py
mongospecs/helpers/empty.py
mongospecs/helpers/ops.py
mongospecs/helpers/pagination.py
mongospecs/helpers/query.py
mongospecs/helpers/se.py
mongospecs/mixins/base.py
mongospecs/mixins/crud.py
mongospecs/mixins/index.py
mongospecs/mixins/integrity.py
mongospecs/mixins/query.py
mongospecs/mixins/session.py
mongospecs/mixins/signal.py
mongospecs/msgspec.py
mongospecs/py.typed
mongospecs/pydantic.py
mongospecs/types.py
mongospecs/utils.py
mongospecs-0.1.4.dist-info/LICENSE
mongospecs-0.1.4.dist-info/METADATA
mongospecs-0.1.4.dist-info/WHEEL
mongospecs-0.1.4.dist-info/RECORD
