Metadata-Version: 2.1
Name: mongospecs
Version: 0.1.4
Summary: simple mongo ODM with support for msgspec, pydantic, and attrs
Home-page: https://github.com/jaykv/mongospecs
Author: Jay
Author-email: jay.github0@gmail.com
Requires-Python: >=3.9,<4.0
Classifier: Programming Language :: Python :: 3
Classifier: Programming Language :: Python :: 3.9
Classifier: Programming Language :: Python :: 3.10
Classifier: Programming Language :: Python :: 3.11
Classifier: Programming Language :: Python :: 3.12
Classifier: Programming Language :: Python :: 3.13
Requires-Dist: blinker (>=1.6.3,<2.0.0)
Requires-Dist: methodtools (>=0.4.7,<0.5.0)
Requires-Dist: msgspec (>=0.18.4,<0.19.0)
Requires-Dist: pymongo (>=4.5.0,<5.0.0)
Requires-Dist: typing-extensions (>=4.8.0,<5.0.0)
Project-URL: Repository, https://github.com/jaykv/mongospecs
